singlesource/__init__.py
singlesource/attestations.py
singlesource/config.py
singlesource/dids.py
singlesource/idrs.py
singlesource/utils.py
singlesource/scripts/__init__.py
singlesource/scripts/attestations.py
singlesource/scripts/dids.py
singlesource/scripts/singlesource_cli.py
pysinglesource-0.1.3.dist-info/LICENSE.md
pysinglesource-0.1.3.dist-info/METADATA
pysinglesource-0.1.3.dist-info/WHEEL
pysinglesource-0.1.3.dist-info/dependency_links.txt
pysinglesource-0.1.3.dist-info/top_level.txt
pysinglesource-0.1.3.dist-info/RECORD
