Metadata-Version: 2.1
Name: pysinglesource
Version: 0.1.3
Summary: The high level software development kit (SDK) to participate in the decentralised SingleSource identity eco-system in Python.
Home-page: https://bitbucket.org/mysinglesource/pysinglesource.git
Author: Guy K. Kloss
Author-email: guy@mysinglesource.io
License: Apache License 2.0
Keywords: singlesource blockchain data kauri kauriid identity self-sovereign jose jwt jws jwe jwk
Platform: UNKNOWN
Classifier: Development Status :: 3 - Alpha
Classifier: Intended Audience :: Developers
Classifier: Topic :: Utilities
Classifier: License :: OSI Approved :: Apache Software License
Classifier: Programming Language :: Python :: 3
Classifier: Programming Language :: Python :: 3.6
Classifier: Programming Language :: Python :: 3.7
Requires-Dist: pykauriid (>=0.3.0)
Requires-Dist: base58
Requires-Dist: requests
Provides-Extra: dev
Requires-Dist: bumpversion ; extra == 'dev'
Requires-Dist: flake8 ; extra == 'dev'
Requires-Dist: flake8-docstrings ; extra == 'dev'
Requires-Dist: pep8-naming ; extra == 'dev'
Requires-Dist: flake8-bugbear ; extra == 'dev'
Requires-Dist: pypi-publisher ; extra == 'dev'
Requires-Dist: pre-commit ; extra == 'dev'
Provides-Extra: test
Requires-Dist: nose2 ; extra == 'test'
Requires-Dist: nose2-cov ; extra == 'test'
